pynliner/__init__.py
pynliner/soupselect.py
pynliner-0.7.2.dist-info/DESCRIPTION.rst
pynliner-0.7.2.dist-info/METADATA
pynliner-0.7.2.dist-info/RECORD
pynliner-0.7.2.dist-info/WHEEL
pynliner-0.7.2.dist-info/metadata.json
pynliner-0.7.2.dist-info/top_level.txt
