Metadata-Version: 2.0
Name: pynliner
Version: 0.7.2
Summary: Python CSS-to-inline-styles conversion tool for HTML using BeautifulSoup and cssutils
Home-page: UNKNOWN
Author: Tanner Netterville
Author-email: tannern@gmail.com
License: MIT
Platform: UNKNOWN
Classifier: Development Status :: 5 - Production/Stable
Classifier: Intended Audience :: Developers
Classifier: License :: OSI Approved :: MIT License
Classifier: Topic :: Text Processing :: Markup :: HTML
Classifier: Programming Language :: Python
Classifier: Programming Language :: Python :: 2.6
Classifier: Programming Language :: Python :: 2.7
Classifier: Programming Language :: Python :: 3
Classifier: Programming Language :: Python :: 3.3
Classifier: Programming Language :: Python :: 3.4
Classifier: Programming Language :: Python :: 3.5
Requires-Dist: BeautifulSoup4 (>=4.4.1)
Requires-Dist: cssutils (>=0.9.7)
